AUTHORS
LICENSE
MANIFEST.in
README.rst
setup.py
pulsus/__init__.py
pulsus.egg-info/PKG-INFO
pulsus.egg-info/SOURCES.txt
pulsus.egg-info/dependency_links.txt
pulsus.egg-info/not-zip-safe
pulsus.egg-info/requires.txt
pulsus.egg-info/top_level.txt
pulsus/client/__init__.py
pulsus/client/client.py
pulsus/server/__init__.py
pulsus/server/serve.py
pulsus/server/server.py
pulsus/server/wsgi.py
pulsus/services/__init__.py
pulsus/services/apns/__init__.py
pulsus/services/apns/notification.py
pulsus/services/apns/service.py
pulsus/services/base/__init__.py
pulsus/services/base/notification.py
pulsus/services/base/service.py
pulsus/services/gcm/__init__.py
pulsus/services/gcm/notification.py
pulsus/services/gcm/service.py