Metadata-Version: 1.1
Name: pulsus
Version: 0.1.0
Summary: Push Notification Service handling Apple Push Notification Service (APNS), and Google Cloud Messaging (GCM).
Home-page: https://github.com/pennersr/pulsus
Author: Raymond Penners
Author-email: raymond.penners@intenct.nl
License: UNKNOWN
Keywords: push notifications apns gcm
Platform: UNKNOWN
Classifier: Development Status :: 4 - Beta
Classifier: Intended Audience :: Developers
Classifier: Topic :: Software Development :: Libraries :: Python Modules
Classifier: Environment :: Web Environment
Classifier: Topic :: Internet
Classifier: License :: OSI Approved :: MIT License
Classifier: Operating System :: OS Independent
Classifier: Programming Language :: Python
Classifier: Programming Language :: Python :: 2.7
